ghostml/__init__.py
ghostml/ghost.py
ghostml-0.3.0.dist-info/LICENSE
ghostml-0.3.0.dist-info/METADATA
ghostml-0.3.0.dist-info/WHEEL
ghostml-0.3.0.dist-info/top_level.txt
ghostml-0.3.0.dist-info/RECORD
