Metadata-Version: 2.1
Name: ghostml
Version: 0.3.0
Summary: UNKNOWN
Home-page: https://github.com/rinikerlab/GHOST
Author: Carmen Esposito
Maintainer: Greg Landrum
License: MIT
Project-URL: Bug Tracker, https://github.com/rinikerlab/GHOST/issues
Project-URL: Source Code, https://github.com/rinikerlab/GHOST
Platform: UNKNOWN
Classifier: Programming Language :: Python :: 3
Classifier: License :: OSI Approved :: MIT License
Classifier: Operating System :: OS Independent
Requires-Python: >=3.6
License-File: LICENSE
Requires-Dist: numpy
Requires-Dist: pandas
Requires-Dist: scikit-learn (>=0.22)
